{
  "BC6T6L-UY8gC": {
    "Name": "Caren Helbing",
    "total_new": "1",
    "publications": {
      "S16KYo8Pm5AC": {
        "title": "Surveillance of European green crab (Carcinus maenas) and monitoring of three native crab species using different environmental DNA collection methods",
        "year": "2025/8/30",
        "publisher": "Global Ecology and Conservation",
        "author": "Mark Louie D Lopez, Nathaniel Zamora, Amy Migneault, Graeme K Knowles, Jacob J Imbery, Eleanor Brouard-John, Zachary Hummel, Kalina Hunter, Sibylla Helms, Caren C Helbing",
        "url": "https://www.sciencedirect.com/science/article/pii/S2351989425004342",
        "firstOrLast": true,
        "datasource": "Scholars"
      }
    }
  },
  "MNqeC0sAAAAJ": {
    "Name": "Robert Michael McKay",
    "total_new": "1",
    "publications": {
      "_5tno0g5mFcC": {
        "title": "Review 3:\" West Nile Virus (Orthoflavivirus nilense) RNA Concentrations in Wastewater Solids at Five Wastewater Treatment Plants in the United States\"",
        "year": "2025/5/13",
        "publisher": "Rapid Reviews Infectious Diseases",
        "author": "Robert McKay",
        "url": "https://rrid.mitpress.mit.edu/pub/08jd3fp0/release/1",
        "firstOrLast": false,
        "datasource": "Scholars"
      }
    }
  },
  "S2HhkvEAAAAJ": {
    "Name": "Sarah Dorner",
    "total_new": "1",
    "publications": {
      "Fu2w8maKXqMC": {
        "title": "Influence of antimicrobial consumption (AMC) on the detection of antimicrobial resistance genes (ARGs) in urban wastewater",
        "year": "2025/7/1",
        "publisher": "International Journal of Hygiene and Environmental Health",
        "author": "Helena Ferreira Leal, \u00c9lise Fortin, Sarah Dorner, Dominic Frigon, Caroline Quach, Emilie B\u00e9dard",
        "url": "https://www.sciencedirect.com/science/article/pii/S1438463925001038",
        "firstOrLast": false,
        "datasource": "Scholars"
      }
    }
  },
  "BZgRYfkAAAAJ": {
    "Name": "Dominic Frigon",
    "total_new": "1",
    "publications": {
      "kO05sadLmrgC": {
        "title": "Influence of antimicrobial consumption (AMC) on the detection of antimicrobial resistance genes (ARGs) in urban wastewater",
        "year": "2025/7/1",
        "publisher": "International Journal of Hygiene and Environmental Health",
        "author": "Helena Ferreira Leal, \u00c9lise Fortin, Sarah Dorner, Dominic Frigon, Caroline Quach, Emilie B\u00e9dard",
        "url": "https://www.sciencedirect.com/science/article/pii/S1438463925001038",
        "firstOrLast": false,
        "datasource": "Scholars"
      }
    }
  }
}